{
  "name": "ethchain-geth.public.dappnode.eth",
  "version": "10.0.15",
  "upstream": "v1.10.0",
  "autoupdate": true,
  "title": "Ethereum node (Geth + mainnet)",
  "description": "Ethereum Client - based on Geth",
  "avatar": "/ipfs/QmVQUEapZGZ7tWfDWP4XUQBxCe2rLbdPJLXu3QaLiPp542",
  "type": "library",
  "chain": "ethereum",
  "image": {
    "path": "ethchain-geth.public.dappnode.eth_10.0.15.tar.xz",
    "hash": "/ipfs/QmbQyrhzeG5EEqTPf4LsciwQ42UFfC2GCEQJ7ms2dFfMfd",
    "size": 29652996,
    "restart": "always",
    "ports": [
      "30303:30303",
      "30303:30303/udp"
    ],
    "volumes": [
      "ethchain-geth:/root/.ethereum/ethchain-geth"
    ],
    "environment": [
      "EXTRA_OPTS=--rpcapi eth,net,web3,txpool"
    ]
  },
  "author": "AVADO",
  "license": "(C)",
  "links": {
    "RPC endpoint": "http://my.ethchain-geth.public.dappnode.eth:8545",
    "RPC endpoint (SSL)": "https://my.ethchain-geth.public.dappnode.eth"
  },
  "builddate": "2021-03-02T20:17:38.795Z"
}